scrapoxy/__init__.py
scrapoxy/api.py
scrapoxy/blacklist.py
scrapoxy/proxy.py
scrapoxy/scale.py
scrapoxy/sticky.py
scrapoxy-2.0.4.dist-info/LICENCE
scrapoxy-2.0.4.dist-info/METADATA
scrapoxy-2.0.4.dist-info/WHEEL
scrapoxy-2.0.4.dist-info/top_level.txt
scrapoxy-2.0.4.dist-info/RECORD
